{"Best Motion Picture": {"Winner": ["Buddy Adler", "Columbia Pictures, From Here to Eternity"], "Nominees": [["John Houseman", "Metro-Goldwyn-Mayer, Julius Caesar"], ["Frank Ross", "20th Century Fox, The Robe"], ["William Wyler", "Paramount Pictures, Roman Holiday"], ["George Stevens", "Paramount Pictures, Shane"]]}, "Best Director": {"Winner": ["From Here to Eternity", "Fred Zinnemann"], "Nominees": [["Lili", "Charles Walters"], ["Roman Holiday", "William Wyler"], ["Shane", "George Stevens"], ["Stalag 17", "Billy Wilder"]]}, "Best Actor": {"Winner": ["Stalag 17", "William Holden"], "Nominees": [["Julius Caesar, Mark Antony", "Marlon Brando"], ["The Robe", "Richard Burton"], ["From Here to Eternity", "Montgomery Clift"], ["From Here to Eternity", "Burt Lancaster"]]}, "Best Actress": {"Winner": ["Roman Holiday", "Audrey Hepburn"], "Nominees": [["Lili", "Leslie Caron"], ["Mogambo", "Ava Gardner"], ["From Here to Eternity", "Deborah Kerr"], ["The Moon Is Blue", "Maggie McNamara"]]}, "Best Supporting Actor": {"Winner": ["From Here to Eternity", "Frank Sinatra"], "Nominees": [["Roman Holiday", "Eddie Albert"], ["Shane", "Brandon deWilde"], ["Shane", "Jack Palance"], ["Stalag 17", "Robert Strauss"]]}, "Best Supporting Actress": {"Winner": ["From Here to Eternity", "Donna Reed"], "Nominees": [["Mogambo", "Grace Kelly"], ["Hondo", "Geraldine Page"], ["Torch Song", "Marjorie Rambeau"], ["Pickup on South Street", "Thelma Ritter"]]}, "Best Screenplay": {"Winner": ["From Here to Eternity", "Daniel Taradash, From Here to Eternity, James Jones"], "Nominees": [["The Cruel Sea", "Eric Ambler, The Cruel Sea, Nicholas Monsarrat"], ["Lili", "Helen Deutsch, Paul Gallico"], ["Roman Holiday", "Ian McLellan Hunter, John Dighton, Dalton Trumbo"], ["Shane", "A. B. Guthrie Jr., Shane, Jack Schaefer"]]}, "Best Story and Screenplay": {"Winner": ["Titanic", "Charles Brackett, Walter Reisch, Richard L. Breen"], "Nominees": [["The Band Wagon", "Betty Comden, Adolph Green"], ["The Desert Rats", "Richard Murphy"], ["The Naked Spur", "Sam Rolfe, Harold Jack Bloom"], ["Take the High Ground!", "Millard Kaufman"]]}, "Best Story": {"Winner": ["Roman Holiday", "Dalton Trumbo"], "Nominees": [["Above and Beyond", "Beirne Lay Jr."], ["The Captain's Paradise", "Alec Coppel"], ["Hondo", "Louis L'Amour"], ["Little Fugitive", "Ray Ashley, Morris Engel, Ruth Orkin"]]}, "Best Short Subject - Cartoons": {"Winner": ["Toot, Whistle, Plunk and Boom", "Walt Disney"], "Nominees": ["From A to Z-Z-Z-Z", "Rugged Bear", "The Tell Tale Heart"]}, "Best Documentary Feature": {"Winner": ["The Living Desert", "Walt Disney"], "Nominees": ["The Conquest of Everest", "A Queen Is Crowned"]}, "Best Documentary Short Subject": {"Winner": ["The Alaskan Eskimo", "Walt Disney"], "Nominees": ["The Living City", "Operation Blue Jay", "They Planted a Stone", "The Word"]}, "Best Live Action Short Subject, One-Reel": {"Winner": ["Overture to The Merry Wives of Windsor", "Johnny Green"], "Nominees": ["Herring Hunt"]}, "Best Live Action Short Subject, Two-Reel": {"Winner": ["Bear Country", "Walt Disney"], "Nominees": ["Ben and Me", "Return to Glennascaul"]}, "Best Music Score of a Dramatic or Comedy Picture": {"Winner": ["Lili", "Bronis\u0142aw Kaper"], "Nominees": [["Above and Beyond", "Hugo Friedhofer"], ["From Here to Eternity", "Morris Stoloff, George Duning"], ["Julius Caesar", "Mikl\u00f3s R\u00f3zsa"], "This Is Cinerama"]}, "Best Scoring of a Musical Picture": {"Winner": ["Call Me Madam", "Alfred Newman"], "Nominees": [["The 5,000 Fingers of Dr. T.", "Frederick Hollander, Morris Stoloff"], ["The Band Wagon", "Adolph Deutsch"], ["Calamity Jane", "Ray Heindorf"], ["Kiss Me Kate", "Andr\u00e9 Previn, Saul Chaplin"]]}, "Best Song": {"Winner": ["Secret Love", "Calamity Jane, Sammy Fain, Paul Francis Webster"], "Nominees": [["The Moon Is Blue", "Herschel Burke Gilbert, Sylvia Fine"], ["Small Town Girl", "Nicholas Brodszky, Leo Robin"], ["Miss Sadie Thompson", "Ned Washington"], ["That's Amore", "The Caddy, Harry Warren, Jack Brooks"]]}, "Best Sound Recording": {"Winner": ["From Here to Eternity", "John P. Livadary"], "Nominees": [["Calamity Jane", "William A. Mueller"], ["Knights of the Round Table", "A. W. Watkins"], ["The Mississippi Gambler", "Leslie I. Carey"], ["The War of the Worlds", "Loren L. Ryder"]]}, "Best Art Direction, Black-and-White": {"Winner": ["Julius Caesar", "Cedric Gibbons, Edward Carfagno, Edwin B. Willis, Hugh Hunt"], "Nominees": [["Martin Luther", "Fritz Maurischat, Paul Markwitz"], ["The President's Lady", "Lyle R. Wheeler, Leland Fuller, Paul S. Fox"], ["Roman Holiday", "Hal Pereira, Walter Tyler"], ["Titanic", "Lyle R. Wheeler, Maurice Ransford, Stuart A. Reiss"]]}, "Best Art Direction, Color": {"Winner": ["The Robe", "Lyle R. Wheeler, George Davis, Walter M. Scott, Paul S. Fox"], "Nominees": [["Knights of the Round Table", "Alfred Junge, Hans Peters, John Jarvis"], ["Lili", "Cedric Gibbons, Paul Groesse, Edwin B. Willis, Arthur Krams"], ["The Story of Three Loves", "Cedric Gibbons, E. Preston Ames, Edward Carfagno, Gabriel Scognamillo, Edwin B. Willis, F. Keogh Gleason, Arthur Krams, Jack D. Moore"], ["Young Bess", "Cedric Gibbons, Urie McCleary, Edwin B. Willis, Jack D. Moore"]]}, "Best Cinematography, Black-and-White": {"Winner": ["From Here to Eternity", "Burnett Guffey"], "Nominees": [["The Four Poster", "Hal Mohr"], ["Julius Caesar", "Joseph Ruttenberg"], ["Martin Luther", "Joseph C. Brun"], ["Roman Holiday", "Franz Planer, Henri Alekan"]]}, "Best Cinematography, Color": {"Winner": ["Shane", "Loyal Griggs"], "Nominees": [["All the Brothers Were Valiant", "George Folsey"], ["Beneath the 12-Mile Reef", "Edward Cronjager"], "Lili", ["The Robe", "Leon Shamroy"]]}, "Best Costume Design, Black-and-White": {"Winner": ["Roman Holiday", "Edith Head"], "Nominees": [["The Actress", "Walter Plunkett"], ["Dream Wife", "Helen Rose, Herschel McCoy"], ["From Here to Eternity", "Jean Louis"], ["The President's Lady", "Charles LeMaire, Reni\u00e9"]]}, "Best Costume Design, Color": {"Winner": ["The Robe", "Charles LeMaire, Emile Santiago"], "Nominees": [["The Band Wagon", "Mary Ann Nyberg"], ["Call Me Madam", "Irene Sharaff"], ["How to Marry a Millionaire", "Charles LeMaire, William Travilla"], ["Young Bess", "Walter Plunkett"]]}, "Best Film Editing": {"Winner": ["From Here to Eternity", "William Lyon"], "Nominees": [["Crazylegs", "Irvine (Cotton) Warburton"], ["The Moon Is Blue", "Otto Ludwig"], ["Roman Holiday", "Robert Swink"], "The War of the Worlds"]}, "Best Special Effects": {"Winner": "The War of the Worlds", "Nominees": []}}