{"Best Picture": {"Winner": ["The Artist", "Thomas Langmann"], "Nominees": [["The Descendants", "Jim Burke, Jim Taylor, Alexander Payne"], ["Extremely Loud & Incredibly Close", "Scott Rudin"], ["The Help", "Brunson Green, Chris Columbus, Michael Barnathan"], ["Hugo", "Graham King, Martin Scorsese"], ["Midnight in Paris", "Letty Aronson, Stephen Tenenbaum"], ["Moneyball", "Michael De Luca, Rachael Horovitz, Brad Pitt"], ["The Tree of Life", "Dede Gardner, Sarah Green, Grant Hill, Bill Pohlad"], ["War Horse", "Steven Spielberg, Kathleen Kennedy"]]}, "Best Director": {"Winner": ["The Artist", "Michel Hazanavicius"], "Nominees": [["The Descendants", "Alexander Payne"], ["Hugo", "Martin Scorsese"], ["Midnight in Paris", "Woody Allen"], ["The Tree of Life", "Terrence Malick"]]}, "Best Actor": {"Winner": ["The Artist", "Jean Dujardin"], "Nominees": [["A Better Life", "Demi\u00e1n Bichir"], ["The Descendants", "George Clooney"], ["Tinker Tailor Soldier Spy, George Smiley", "Gary Oldman"], ["Moneyball, Billy Beane", "Brad Pitt"]]}, "Best Actress": {"Winner": ["The Iron Lady, Margaret Thatcher", "Meryl Streep"], "Nominees": [["Albert Nobbs", "Glenn Close"], ["The Help", "Viola Davis"], ["The Girl with the Dragon Tattoo, Lisbeth Salander", "Rooney Mara"], ["My Week with Marilyn, Marilyn Monroe", "Michelle Williams"]]}, "Best Supporting Actor": {"Winner": ["Beginners", "Christopher Plummer"], "Nominees": [["My Week with Marilyn, Laurence Olivier", "Kenneth Branagh"], ["Moneyball, Peter Brand", "Jonah Hill"], ["Warrior", "Nick Nolte"], ["Extremely Loud & Incredibly Close", "Max von Sydow"]]}, "Best Supporting Actress": {"Winner": ["The Help", "Octavia Spencer"], "Nominees": [["The Artist", "B\u00e9r\u00e9nice Bejo"], ["The Help", "Jessica Chastain"], ["Bridesmaids", "Melissa McCarthy"], ["Albert Nobbs", "Janet McTeer"]]}, "Best Original Screenplay": {"Winner": ["Midnight in Paris", "Woody Allen"], "Nominees": [["The Artist", "Michel Hazanavicius"], ["Bridesmaids", "Kristen Wiig, Annie Mumolo"], ["Margin Call", "J. C. Chandor"], ["A Separation", "Asghar Farhadi"]]}, "Best Adapted Screenplay": {"Winner": ["The Descendants", "Alexander Payne, Nat Faxon, Jim Rash, the novel, Kaui Hart Hemmings"], "Nominees": [["Hugo", "John Logan, The Invention of Hugo Cabret, Brian Selznick"], ["The Ides of March", "George Clooney, Grant Heslov, Beau Willimon, Farragut North, Beau Willimon"], ["Moneyball", "Steven Zaillian, Aaron Sorkin, Stan Chervin, the book, Michael Lewis"], ["Tinker Tailor Soldier Spy", "Bridget O'Connor, Peter Straughan, the novel, John le Carr\u00e9"]]}, "Best Animated Feature Film": {"Winner": ["Rango", "Gore Verbinski"], "Nominees": [["A Cat in Paris", "Alain Gagnol, Jean-Loup Felicioli"], ["Chico and Rita", "Fernando Trueba, Javier Mariscal"], ["Kung Fu Panda 2", "Jennifer Yuh Nelson"], ["Puss in Boots", "Chris Miller"]]}, "Best Foreign Language Film": {"Winner": ["A Separation", "Iran, Persian, Asghar Farhadi"], "Nominees": [["Bullhead", "Belgium, Dutch, Micha\u00ebl R. Roskam"], ["Footnote", "Israel, Hebrew, Joseph Cedar"], ["In Darkness", "Poland, Agnieszka Holland"], ["Monsieur Lazhar", "Canada, Philippe Falardeau"]]}, "Best Documentary \u2013 Feature": {"Winner": ["Undefeated", "T. J. Martin, Daniel Lindsay, Rich Middlemas"], "Nominees": [["Hell and Back Again", "Danfung Dennis, Mike Lerner"], ["If a Tree Falls: A Story of the Earth Liberation Front", "Marshall Curry, Sam Cullman"], ["Paradise Lost 3: Purgatory", "Joe Berlinger, Bruce Sinofsky"], ["Pina", "Wim Wenders, Gian-Piero Ringel"]]}, "Best Documentary \u2013 Short Subject": {"Winner": ["Saving Face", "Sharmeen Obaid-Chinoy, Daniel Junge"], "Nominees": [["The Barber of Birmingham", "Robin Fryday, Gail Dolgin"], ["God Is the Bigger Elvis", "Rebecca Cammisa, Julie Anderson"], ["Incident in New Baghdad", "James Spione"], ["The Tsunami and the Cherry Blossom", "Lucy Walker, Kira Carstensen"]]}, "Best Live Action Short Film": {"Winner": ["The Shore", "Terry George, Oorlagh George"], "Nominees": [["Pentecost", "Peter McDonald, Eimear O'Kane"], ["Raju", "Max Zahle, Stefan Gieren"], ["Time Freak", "Andrew Bowler, Gigi Causey"], ["Tuba Atlantic", "Hallvar Witz\u00f8, [c]"]]}, "Best Animated Short Film": {"Winner": ["The Fantastic Flying Books of Mr. Morris Lessmore", "William Joyce, Brandon Oldenburg"], "Nominees": [["Dimanche", "Patrick Doyon"], ["La Luna", "Enrico Casarosa"], ["A Morning Stroll", "Grant Orchard, Sue Goffe"], ["Wild Life", "Amanda Forbis, Wendy Tilby"]]}, "Best Original Score": {"Winner": ["The Artist", "Ludovic Bource"], "Nominees": [["The Adventures of Tintin", "John Williams"], ["Hugo", "Howard Shore"], ["Tinker Tailor Soldier Spy", "Alberto Iglesias"], ["War Horse", "John Williams"]]}, "Best Original Song": {"Winner": ["Man or Muppet", "The Muppets, Bret McKenzie"], "Nominees": [["Rio", "S\u00e9rgio Mendes, Carlinhos Brown, Siedah Garrett"]]}, "Best Sound Editing": {"Winner": ["Hugo", "Philip Stockton, Eugene Gearty"], "Nominees": [["Drive", "Lon Bender, Victor Ray Ennis"], ["The Girl with the Dragon Tattoo", "Ren Klyce"], ["Transformers: Dark of the Moon", "Ethan Van der Ryn, Erik Aadahl"], ["War Horse", "Richard Hymns, Gary Rydstrom"]]}, "Best Sound Mixing": {"Winner": ["Hugo", "Tom Fleischman, John Midgley"], "Nominees": [["The Girl with the Dragon Tattoo", "David Parker, Michael Semanick, Ren Klyce, Bo Persson"], ["Moneyball", "Deb Adair, Ron Bochar, David Giammarco, Ed Novick"], ["Transformers: Dark of the Moon", "Greg P. Russell, Gary Summers, Jeffrey J. Haboush, Peter J. Devlin"], ["War Horse", "Gary Rydstrom, Andy Nelson, Tom Johnson, Stuart Wilson"]]}, "Best Art Direction": {"Winner": ["Hugo", "Art Direction, Dante Ferretti, Set Decoration, Francesca Lo Schiavo"], "Nominees": [["The Artist", "Laurence Bennett, Robert Gould"], ["Harry Potter and the Deathly Hallows \u2013 Part 2", "Stuart Craig, Stephenie McMillan"], ["Midnight in Paris", "Anne Seibel, H\u00e9l\u00e8ne Dubreuil"], ["War Horse", "Rick Carter, Lee Sandales"]]}, "Best Cinematography": {"Winner": ["Hugo", "Robert Richardson"], "Nominees": [["The Artist", "Guillaume Schiffman"], ["The Girl With the Dragon Tattoo", "Jeff Cronenweth"], ["The Tree of Life", "Emmanuel Lubezki"], ["War Horse", "Janusz Kami\u0144ski"]]}, "Best Makeup": {"Winner": ["The Iron Lady", "Mark Coulier, J. Roy Helland"], "Nominees": [["Albert Nobbs", "Martial Corneville, Lynn Johnson, Matthew W. Mungle"], ["Harry Potter and the Deathly Hallows \u2013 Part 2", "Nick Dudman, Amanda Knight, Lisa Tomblin"]]}, "Best Costume Design": {"Winner": ["The Artist", "Mark Bridges"], "Nominees": [["Anonymous", "Lisy Christl"], ["Hugo", "Sandy Powell"], ["Jane Eyre", "Michael O'Connor"], ["W.E.", "Arianne Phillips"]]}, "Best Film Editing": {"Winner": ["The Girl with the Dragon Tattoo", "Angus Wall, Kirk Baxter"], "Nominees": [["The Artist", "Anne-Sophie Bion, Michel Hazanavicius"], ["The Descendants", "Kevin Tent"], ["Hugo", "Thelma Schoonmaker"], ["Moneyball", "Christopher Tellefsen"]]}, "Best Visual Effects": {"Winner": ["Hugo", "Robert Legato, Joss Williams, Ben Grossmann, Alex Henning"], "Nominees": [["Harry Potter and the Deathly Hallows \u2013 Part 2", "Tim Burke, David Vickery, Greg Butler, John Richardson"], ["Real Steel", "Erik Nash, Dan Taylor, Swen Gillberg"], ["Rise of the Planet of the Apes", "Joe Letteri, Dan Lemmon, R. Christopher White, Daniel Barrett"], ["Transformers: Dark of the Moon", "Scott Farrar, Scott Benza, Matthew E. Butler, John Frazier"]]}}